cnmpdk/__init__.py
cnmpdk/cnm_layer_views.yaml
cnmpdk/config.py
cnmpdk/materials.py
cnmpdk/tech.py
cnmpdk/ip_blocks/CNM_library_v6.1.1_BB_MPW_06_07-07-2022_CNMPDK.gds
cnmpdk/ip_blocks/__init__.py
cnmpdk/ip_blocks/cnmD2SBB_1to1.py
cnmpdk/ip_blocks/cnmD2SBB_1to2.py
cnmpdk/ip_blocks/cnmD2SBB_1to3.py
cnmpdk/ip_blocks/cnmINVTAP_10_0.py
cnmpdk/ip_blocks/cnmMMI1585_BB.py
cnmpdk/ip_blocks/cnmMMI1x2DE_BB.py
cnmpdk/ip_blocks/cnmMMI1x2SH_BB.py
cnmpdk/ip_blocks/cnmMMI2x2DE_BB.py
cnmpdk/ip_blocks/cnmMMI2x2SH_BB.py
cnmpdk/ip_blocks/cnmMMI3x3DE_BB.py
cnmpdk/ip_blocks/cnmMMI3x3SH_BB.py
cnmpdk/ip_blocks/cnmMMI8515_BB.py
cnmpdk/ip_blocks/cnmS2DBB_1to1.py
cnmpdk/ip_blocks/cnmS2DBB_2to1.py
cnmpdk/ip_blocks/cnmS2DBB_3to1.py
cnmpdk/klayout/cnm_klayout_layers.lyp
cnmpdk/klayout/cnm_technology.lyt
cnmpdk/pcells/__init__.py
cnmpdk/pcells/cnm_die_10x5.py
cnmpdk-0.2.0.dist-info/LICENSE
cnmpdk-0.2.0.dist-info/METADATA
cnmpdk-0.2.0.dist-info/WHEEL
cnmpdk-0.2.0.dist-info/top_level.txt
cnmpdk-0.2.0.dist-info/RECORD
