Metadata-Version: 2.1
Name: cnmpdk
Version: 0.2.0
Summary: CNM PDK for gdsfactory
Home-page: https://github.com/mario26z/cnm.git
Author: Mario Mejias
Author-email: mario.mejias@vlcphotonics.com
Classifier: Programming Language :: Python :: 3
Classifier: License :: OSI Approved :: MIT License
Classifier: Operating System :: OS Independent
Requires-Python: >=3.11
License-File: LICENSE
Requires-Dist: gdsfactory (>9.0.0)
